{
    "filename": "0000126164.jpg",
    "metadata": {},
    "text": " \n\n \n\n \n\nney Ta Sage Ge x Genaeh\n‘ecg sig degear or\n\n \n\n \n\nUANN-ERICKSON RESP EP\n\n \n\n \n\n \n\n \n\n \n\n \n\n \n\n   \n\n \n\n \n\n \n\n \n\n \n\n \n\n \n\n \n\nPSTe-g> _ | arraows [seuarune | pare!\n—\nix oft Coupon ares\nBsc 1 iS\n33.68. | i {\nee > VP. Brand Management i -\nBy,\npe\n: —\n\n670117498\naa\n\n \n\f",
    "augmented_texts": [
        "ney Ta Sage Ge x Genaeh ‘ ecg sig degear or UANN - ERICKSON RESP EP PSTe - g> _ | arraows [seuarune | pare! — ix oft Coupon ares Bsc single iS 33. 68. | i {ee> VP. Brand Direction i - By, pe: — 670117498 aa",
        "ney Ta Sage Ge x Genaeh ‘ ecg sig degear or UANN - ERICKSON RESP EP PSTe - gigabyte> _ | arraows [seuarune | pare! — ix oft Coupon ares Bsc 1 iS 33. 68. | ace {ee> VP. Brand Management i - By, pe: — 670117498 aa"
    ],
    "predicted_cluster": 3,
    "predicted_label": "cluster_3",
    "summary": "ney Ta Sage Ge x Genaeh ‘ecg sig degear or’ or. “Coupon ares” are a form of payment for services provided by the company. For confidential support call the National Suicide Prevention Lifeline on 1-800-273-8255 or visit http://www.suicidepreventionlifeline.org/."
}