{
    "filename": "82624369.jpg",
    "metadata": {},
    "text": "5/12/2000\n\nCORP. & DIRECT\n\nMSA SETTLEMENT\neee\nACTUAL ESTIMATED *\nQUTDOOR RENT APRIL MAY-DEC\n\nTRIBORO BRIDGE - ARTKRAFT\n\nBLACK PUBLICATIONS\n\nsce 2,500.00\n\nMISCELLANEQUS_ MAINTENANCE\n\nDIRECT TOTAL 2,500.00, 0.00\nGRAND TOTAL 2,500.00 0.00 2,500.00 :\n* SUBJECT TO CHANGE\n\n69£72978\n\f",
    "augmented_texts": [
        "5 / 12 / 2000 CORP. & DIRECT MSA SETTLEMENT eee ACTUAL ESTIMATED * QUTDOOR RENT APRIL MAY - declination TRIBORO BRIDGE - ARTKRAFT BLACK PUBLICATIONS sce 2, 500. 00 MISCELLANEQUS_ care DIRECT TOTAL 2, 500. 00, 0. 00 GRAND TOTAL 2, 500. 00 0. 00 two, 500. 00: * SUBJECT TO modification 69 £ 72978",
        "5 / 12 / 2000 CORP. & DIRECT MSA SETTLEMENT eee ACTUAL ESTIMATED * QUTDOOR RENT apr MAY - celestial latitude TRIBORO BRIDGE - ARTKRAFT BLACK PUBLICATIONS sce 2, 500. 00 MISCELLANEQUS_ MAINTENANCE DIRECT TOTAL 2, 500. 00, cipher. 00 GRAND TOTAL 2, 500. 00 0. 00 2, 500. 00: * SUBJECT TO variety 69 £ 72978"
    ],
    "predicted_cluster": 3,
    "predicted_label": "cluster_3",
    "summary": "5/12/2000: 2,500.00, 0.0005% of the total cost of building the bridge. 5/11/2001: 1,000.0%.0.1%.1,100.5%.2,200.7%.3,300.6%.4,400.8%.5,600.9%.6,700.2.3.4."
}