{
    "filename": "invoice_10489.pdf",
    "metadata": {
        "format": "PDF 1.3",
        "title": "",
        "author": "",
        "subject": "",
        "keywords": "",
        "creator": "",
        "producer": "PyFPDF 1.7.2 http://pyfpdf.googlecode.com/",
        "creationDate": "D:20230529103523",
        "modDate": "",
        "trapped": "",
        "encryption": null
    },
    "text": "Invoice\nOrder ID: 10489\nCustomer ID: PICCO\nOrder Date: 2017-03-28\nCustomer Details:\nContact Name:\nGeorg Pipps\nAddress:\nGeislweg 14\nCity:\nSalzburg\nPostal Code:\n5020\nCountry:\nAustria\nPhone:\n6562-9722\nFax:\n6562-9723\nProduct Details:\nProduct ID\nProduct Name\nQuantity\nUnit Price\n11\nQueso Cabrales\n15\n16.8\n16\nPavlova\n18\n13.9\n \n \nTotalPrice\n502.20000000000005\nPage 1\n",
    "augmented_texts": [
        "Invoice Order gem state: 10489 Customer ID: PICCO Order Date: 2017 - 03 - 28 Customer Details: Contact Name: Georg Pipps Computer address: Geislweg 14 City: Salzburg Postal Code: 5020 Country: Austria Phone: 6562 - 9722 Fax: 6562 - 9723 Product Details: Product ID Product Name Quantity Unit Price xi Queso Cabrales 15 16. 8 16 Pavlova 18 xiii. 9 TotalPrice 502. 20000000000005 Page one",
        "Invoice Order ID: 10489 Client ID: PICCO Order Date: 2017 - 03 - 28 Customer Details: Contact Name: Georg Pipps Address: Geislweg 14 City: Salzburg Postal Code: 5020 Country: Austria Phone: 6562 - 9722 Fax: 6562 - 9723 Product Details: Product ID Product Name Amount Unit Price xi Queso Cabrales 15 16. 8 16 Anna pavlova 18 13. 9 TotalPrice 502. 20000000000005 Page i"
    ],
    "predicted_cluster": 4,
    "predicted_label": "cluster_4",
    "summary": "Invoice Name: PICCO. Order Date: 2017-03-28. Customer Details:Georg Pipps. Phone: 6562-9722.Fax:6562 -9723. Product ID: 10489. Unit Price: 502.20000000000005. Price per item: $0."
}